README.rst
glop/__init__.py
glop/analyzer.py
glop/compiled_grammar_parser.py
glop/compiled_parser_base.py
glop/compiler.py
glop/grammar_printer.py
glop/hand_rolled_grammar_parser.py
glop/host.py
glop/host_fake.py
glop/interpreter.py
glop/main.py
glop/parser_base.py
glop/version.py
glop-0.1.1.dist-info/DESCRIPTION.rst
glop-0.1.1.dist-info/entry_points.txt
glop-0.1.1.dist-info/METADATA
glop-0.1.1.dist-info/metadata.json
glop-0.1.1.dist-info/RECORD
glop-0.1.1.dist-info/top_level.txt
glop-0.1.1.dist-info/WHEEL
