Metadata-Version: 2.0
Name: glop
Version: 0.1.1
Summary: GLOP - the Generalized Lpeg and Ometa-inspired Parsing and printing framework.
Home-page: https://github.com/dpranke/glop
Author: Dirk Pranke
Author-email: dpranke@chromium.org
License: Apache
Platform: UNKNOWN
Classifier: Development Status :: 3 - Alpha
Classifier: Intended Audience :: Developers
Classifier: License :: OSI Approved :: Apache Software License
Classifier: Programming Language :: Python :: 2
Classifier: Programming Language :: Python :: 2.7
Classifier: Programming Language :: Python :: 3
Classifier: Programming Language :: Python :: 3.4
Classifier: Topic :: Software Development :: Compilers
Classifier: Topic :: Software Development :: Interpreters
Classifier: Topic :: Text Processing :: Filters
